cogniceptshell/__init__.py
cogniceptshell/agent_life_cycle.py
cogniceptshell/common.py
cogniceptshell/configuration.py
cogniceptshell/interface.py
cogniceptshell/ota_updater.py
cogniceptshell/pusher.py
cogniceptshell/robot_actions.py
cogniceptshell/rosbag_record.py
tests/__init__.py
tests/unit/__init__.py
tests/unit/mock_docker_client.py
tests/unit/test_config.py
tests/unit/test_event_log.py
tests/unit/test_get_disk_space.py
tests/unit/test_get_robot_org_id.py
tests/unit/test_keyrotate.py
tests/unit/test_lifecycle.py
tests/unit/test_move.py
tests/unit/test_ota_deployment.py
tests/unit/test_populate_config_files.py
tests/unit/test_pull_config_templates.py
tests/unit/test_version_update.py
cognicept_shell-1.8.0.dist-info/LICENSE.txt
cognicept_shell-1.8.0.dist-info/METADATA
cognicept_shell-1.8.0.dist-info/WHEEL
cognicept_shell-1.8.0.dist-info/entry_points.txt
cognicept_shell-1.8.0.dist-info/top_level.txt
cognicept_shell-1.8.0.dist-info/RECORD
