Metadata-Version: 2.1
Name: cognicept-shell
Version: 1.8.0
Summary: Shell utility to configure Cognicept tools.
Home-page: https://kabam.ai
Author: Jakub Tomasek
License: Apache License 2.0
Platform: UNKNOWN
Classifier: Development Status :: 3 - Alpha
Classifier: Intended Audience :: Developers
Classifier: Intended Audience :: System Administrators
Classifier: Natural Language :: English
Classifier: License :: OSI Approved :: Apache Software License
Classifier: Programming Language :: Python
Classifier: Programming Language :: Python :: 3
Classifier: Programming Language :: Python :: 3.3
Classifier: Programming Language :: Python :: 3.4
Classifier: Programming Language :: Python :: 3.5
Classifier: Programming Language :: Python :: 3.6
Classifier: Programming Language :: Python :: 3.8
Classifier: Programming Language :: Python :: 3.10
Requires-Dist: PyCryptodome (>=3.9.8)
Requires-Dist: PyJWT (==1.7.1)
Requires-Dist: argcomplete (>=1.12.3)
Requires-Dist: boto3 (>=1.14.0)
Requires-Dist: docker (==5.0.3)
Requires-Dist: paramiko (>=2.4.2)
Requires-Dist: ping3
Requires-Dist: psutil
Requires-Dist: pyaml
Requires-Dist: python-dotenv (==0.14.0)
Requires-Dist: ruamel.yaml
Requires-Dist: tabulate
Requires-Dist: urllib3 (==1.25.4)
Requires-Dist: websocket-client (==0.59.0)
